Workbook
Name f: #REF!
Name GruppeA_farve: #REF!
Name GruppeB_farve: #REF!

Sheet Forside
A1: Kriterium navn | B1: Kriterium forkortelse | C1: Kriterium vægtning (0-5) | D1: Samlet kriterium score
A2: Klimaforandringer | B2: =Matrix!A2 -> E1 | C2: =ROUNDDOWN(AVERAGE(DVA!B2:C2),0) -> 1 | D2: =Matrix!G2 -> 100
A3: Forurening | B3: =Matrix!A26 -> E2 | C3: =ROUNDDOWN(AVERAGE(DVA!B3:C3),0) -> 0 | D3: =Matrix!G26 -> 100
A4: Vand- og havressourcer | B4: =Matrix!A51 -> E3 | C4: =ROUNDDOWN(AVERAGE(DVA!B4:C4),0) -> 1 | D4: =Matrix!G51 -> 100
A5: Biodiversitet og økosystemer | B5: =Matrix!A57 -> E4 | C5: =ROUNDDOWN(AVERAGE(DVA!B5:C5),0) -> 2 | D5: =Matrix!G57 -> 0
A6: Ressourceanvendelse og cirkulær økonomi | B6: =Matrix!A70 -> E5 | C6: =ROUNDDOWN(AVERAGE(DVA!B6:C6),0) -> 4 | D6: =Matrix!G70 -> 0
A7: Egen arbejdsstyrke | B7: =Matrix!A81 -> S1 | C7: =ROUNDDOWN(AVERAGE(DVA!B7:C7),0) -> 3 | D7: =Matrix!G81 -> 65
A8: Arbejdstagere i værdikæden | B8: =Matrix!A109 -> S2 | C8: =ROUNDDOWN(AVERAGE(DVA!B8:C8),0) -> 3 | D8: =Matrix!G109 -> 45
A9: Berørte samfund | B9: =Matrix!A124 -> S3 | C9: =ROUNDDOWN(AVERAGE(DVA!B9:C9),0) -> 3 | D9: =Matrix!G124 -> 100
A10: Forbrugere og slutbrugere | B10: =Matrix!A133 -> S4 | C10: =ROUNDDOWN(AVERAGE(DVA!B10:C10),0) -> 4 | D10: =Matrix!G133 -> 70
A11: God forretningsskik | B11: =Matrix!A142 -> G1 | C11: =ROUNDDOWN(AVERAGE(DVA!B11:C11),0) -> 2 | D11: =Matrix!G142 -> 70
A12: Samlet score | B12: =SUM(Matrix!I2,Matrix!I26,Matrix!I51,Matrix!I57,Matrix!I70,Matrix!I81,Matrix!I109,Matrix!I124,Matrix!I133,Matrix!I142) -> 52
A14: Virksomhedsnavn | B14: Djurs Consult
A15: Lokation | B15: Hovedkontor
A16: Adresse | B16: Østergade 7, 8963 Auning
A17: Antal ansatte | B17: 23
A18: Årlig omsætning/noget andet | B18: 10000000
A19: Branchekode | B19: 71.12.10 Rådgivende ingeniøraktiviteter inden for byggeri og anlægsarbejder

Sheet DVA_Spørgsmål
B1: Spørgsmål | C1: Ja | D1: Nej | E1: Beskrivelse | F1: Typiske brancher
A2: E1 | B2: Klimaforandringer
A3: Impact | B3: Udleder virksomheden direkte drivhusgasser (CO₂e) i forbindelse med drift, transport eller energiforbrug? | C3: TRUE | D3: FALSE | E3: Gælder hvis virksomheden fx bruger firmabiler, har produktionsudstyr, opvarmer lokaler med olie/gas, eller flyver på firmarejser. Kontorarbejde uden transport tæller ikke. | F3: Transport, byggeri, produktion, landbrug, detail med transport
B4: Forårsager virksomhedens produkter, ydelser eller drift væsentlig indirekte CO₂e-udledning i værdikæden? | C4: TRUE | D4: FALSE | E4: Gælder fx salg af fysiske varer, rådgivning om CO₂-intensive projekter, eller outsourcing af produktion. Kun meget simple servicefag (massør, frisør osv.) undgår dette. | F4: Produktion, engros, rådgivning, detailhandel, byggeri
B5: Tilbyder virksomheden produkter eller ydelser, der kan hjælpe andre med at reducere deres klimaaftryk? | C5: FALSE | D5: TRUE | E5: Gælder fx energirådgivning, klimateknologier, software til måling af emissioner eller klimavenlige produkter. Gælder også ansvar i værdikæden. | F5: Cleantech, konsulenter, energi, grøn transport, IT-software
B6: Er virksomheden aktiv i en branche, der ifølge EU eller Klimarådet er blandt de mest CO₂e-intensive? | C6: FALSE | D6: FALSE | E6: Gælder kun hvis virksomheden er i en af følgende brancher: energi, byggeri, cement, stål, landbrug, transport, minedrift, kemi, plastproduktion, tekstil eller shipping. | F6: Energi, byggeri, cement, stål, landbrug, transport, minedrift, kemi, plastproduktion, tekstil, shipping (liste kan justeres efter national/EU-kilder).
B7: Har virksomheden indvoldveret i aktiviteter, der medfører ændringer i arealanvendelse med betydning for klimaet? | C7: FALSE | D7: TRUE | E7: Gælder fx byggeri, skovrydning, anlægsarbejde, eller store parkeringspladser, som fjerner grønne arealer og påvirker kulstofbinding. | F7: Byggeri, anlæg, landbrug, minedrift, logistikcentre
A8: Finansiel | B8: Kan klimaforandringer medføre betydningsfuldt højere omkostninger for virksomheden (f.eks. energi, forsikring, leverancer)? | C8: TRUE | D8: FALSE | E8: Gælder fx stigende elpriser, forsikringer, transport, eller udgifter til klimatilpasning eller indkøb. | F8: Alle brancher – men især energiintensive
B9: Kan klimarelateret regulering påvirke virksomhedens konkurrenceevne eller krav til produkter? | C9: FALSE | D9: FALSE | E9: Gælder fx CO₂-afgifter, EU's taksonomi, energikrav til bygninger eller dokumentationskrav fra kunder. | F9: Produktion, byggeri, transport, fødevarer, eksport
B10: Har virksomheden drift, hoved- leverandører eller kunder i geografiske områder med risiko for oversvømmelse, tørke eller storme? | C10: FALSE | D10: TRUE | E10: Gælder kun hvis man har produktion, kontor eller nøgleleverandører i områder, som ifølge myndigheder (fx DMI eller EU) er klimarisikozoner. | F10: Landbrug, byggeri, transport, produktion, fødevarer
B11: Kan virksomheden miste eller vinde kunder, investorer eller markedsandele pga. krav om lavt klimaaftryk? | C11: FALSE | D11: FALSE | E11: Gælder hvis virksomheden har kunder, partnere eller investorer, der stiller krav om dokumenteret CO₂-reduktion, klimamærkning eller ESG. | F11: Rådgivning, mode, tech, byggeri, detail, transport, fødevarer
B12: Har virksomheden mulighed for at tjene penge på klimaforandringer (f.eks. via nye markeder, produkter eller ydelser)? | C12: FALSE | D12: FALSE | E12: Gælder fx klimatilpasning, grønne produkter, investeringer i vedvarende energi, eller øget efterspørgsel på rådgivning eller data. | F12: Energi, rådgivning, tech, byggeri, forsyning
A13: E2 | B13: Forurening
A14: Impact | B14: Udleder virksomheden forurenedne stoffer til luft, jord eller vand? | C14: FALSE | D14: TRUE | E14: Gælder direkte udledning fra drift, f.eks. partikler (PM), NOx, SO₂, tungmetaller, næringsstoffer, olie, kemikalier mv. Gælder også udledning fra firmatransport og entreprenørmaskiner, hvis de bruger fossile brændsler og ikke har renseteknologi. Gælder ikke CO₂ eller andre drivhusgasser – de vurderes under E1. | F14: Produktion, industri, byggeri, landbrug, transport, fødevare, varmeværker
B15: Bruger eller producerer virksomheden kemikalier klassificeret som miljøfarlige? | C15: FALSE | D15: TRUE | E15: Omfatter f.eks. PFAS, pesticider, tungmetaller, akvatoksiske stoffer, olier, opløsningsmidler eller kemikalier mærket med miljøfare (GHS09). Almindelige kontorartikler og husholdningsmidler i små mængder tæller ikke. | F15: Kemi, plast, rengøring, landbrug, medicinal, produktion, maling/lak
B16: Håndterer virksomheden processpildevand, farligt affald eller luftfiltrering? | C16: FALSE | D16: TRUE | E16: Dækker hvis virksomheden selv står for behandling, opbevaring eller bortledning af stoffer, der skal håndteres miljømæssigt forsvarligt – fx via renseanlæg, filtre, affaldssortering, beholdere til olie eller kemikalier. | F16: Industri, fødevare, metal, tekstil, affaldsbehandling, vaskerier, byggeri
B17: Skaber virksomhedens aktiviteter målelig støj-, lys- eller lugtforurening i omgivelserne? | C17: TRUE | D17: FALSE | E17: Gælder fx støj fra maskiner, trafik, byggepladser eller events; lysforurening fra natbelysning; lugtgener fra produktion eller affald. Ikke almindelig kontoraktivitet eller internt støjniveau. | F17: Transport, events, restauranter, byggeri, produktion, landbrug
B18: Har virksomheden indflydelse på valg af materialer i produkter eller projekter, hvor miljøskadelige stoffer kan indgå? | C18: FALSE | D18: TRUE | E18: Omfatter hvor virksomheden designer, specificerer eller anbefaler materialer, f.eks. maling, lim, plasttyper eller byggematerialer. Gælder ikke videresalg uden indflydelse på valg. | F18: Arkitekter, ingeniører, designere, konsulenter, entreprenører, byggeri
A19: Finansiel | B19: Påfører virksomhedens udledning til luft, jord eller vand omkostninger eller krav fra myndigheder? | C19: FALSE | D19: TRUE | E19: Ja, hvis der er udledning fra drift (f.eks. partikler, NOx, olie, tungmetaller, kemikalier, næringsstoffer), som kræver tilladelser, kontrol, afgifter, oprensning, eller investering i rense-/filterudstyr. Gælder også udledning fra firmakøretøjer, maskiner eller spildevand. | F19: Produktion, landbrug, byggeri, transport, affald, fødevare, varmeværker
B20: Bruger virksomheden miljøfarlige stoffer, der kan blive ramt af forbud, begrænsninger eller skærpede krav? | C20: FALSE | D20: TRUE | E20: Ja, hvis virksomheden bruger stoffer, der er klassificeret som miljøfarlige (fx PFAS, pesticider, bly, opløsningsmidler, olier, kemikalier mærket GHS09), og disse kan blive begrænset, kræve substitution eller dokumentation. | F20: Kemi, plast, rengøring, medicinal, landbrug, tekstil, produktion, maling
B21: Møder virksomheden kundekrav eller udbudsbetingelser, hvor dokumentation eller begrænsning af forurening er påkrævet? | C21: FALSE | D21: TRUE | E21: Ja, hvis virksomheden skal dokumentere lav forurening (f.eks. miljøvaredeklaration, svanemærkning, REACH, ISO 14001) for at opnå eller fastholde ordrer, certificeringer eller udbud. | F21: Byggeri, eksport, B2B-produktion, rådgivere, møbel, tekstil, fødevare
B22: Tilbyder virksomheden produkter eller ydelser, der reducerer miljøforurening ift. standardløsninger? | C22: FALSE | D22: TRUE | E22: Ja, hvis virksomheden producerer eller sælger løsninger, der beviseligt reducerer forurening (fx lav-emissionsprodukter, kemikaliefri alternativer, filtrering, grøn transport, rådgivning i substitution). Gælder kun hvis dokumentationen foreligger eller kræves af kunder. | F22: Cleantech, affald, teknologi, produktionsudstyr, rådgivning, byggeri
B23: Kan virksomheden opnå tilskud, skattelettelser, mærkning eller grønne indkøbsaftaler som kræver dokumenterbar lav miljøforurening? | C23: FALSE | D23: TRUE | E23: Ja, hvis virksomheden er omfattet af eller kan opnå konkrete økonomiske fordele (tilskud, grønne ordninger, præferencer i udbud), hvor adgang er betinget af dokumenteret lav udledning eller fravær af miljøfarlige stoffer. | F23: Grøn teknologi, eksportvirksomheder, byggeri, cleantech, miljømærkede produkter
A24: E3 | B24: Vand- og havressourcer
A25: Impact | B25: Bruger virksomheden vand i driften ud over almindeligt kontorforbrug (toilet, rengøring, kaffe mv.)? | C25: FALSE | D25: TRUE | E25: Gælder hvis virksomheden bruger vand i produktion, processer, køling, rengøring, landbrug eller anden drift, hvor vandforbruget er væsentligt. Ikke relevant ved almindelig kontoraktivitet. | F25: Produktion, landbrug, energi, fødevare, tekstil, metal, vaskerier
B26: Har virksomheden drift eller forsyning i områder med vandmangel eller risiko for tørke? | C26: FALSE | D26: TRUE | E26: Omfatter egne lokationer og nøgleleverandører i regioner med dokumenteret vandknaphed, f.eks. Sydeuropa, visse dele af Afrika, Asien eller tørkeramte danske egne. | F26: Landbrug, tekstil, eksport, fødevare, byggeri
B27: Udleder virksomheden stoffer eller affald til havet, eller har aktiviteter til søs eller i kystnære områder? | C27: FALSE | D27: TRUE | E27: Gælder f.eks. udledning fra rensningsanlæg, transport til søs, offshoreaktiviteter eller affaldshåndtering i havmiljøet. Inkluderer også erosion eller forstyrrelse af kystzoner. | F27: Skibsfart, offshore, affald, byggeri, turisme, akvakultur
B28: Er virksomheden aktiv i fiskeri, havbrug eller udnyttelse af marine ressourcer (fisk, skaldyr, tang mv.)? | C28: TRUE | D28: FALSE | E28: Gælder kommercielt fiskeri, akvakultur, tangproduktion eller tilsvarende aktiviteter, uanset om det er direkte eller via underleverandører. | F28: Fiskeri, akvakultur, fødevarer, eksport
B29: Kan virksomhedens aktiviteter forurene vandmiljøet, f.eks. via kemikalier, affald, gødning eller pesticider? | C29: FALSE | D29: TRUE | E29: Omfatter aktiviteter der kan føre til udledning eller afstrømning af miljøfarlige stoffer til vandløb, grundvand eller havmiljø. Gælder også indirekte påvirkning gennem leverandører. | F29: Landbrug, byggeri, kemi, rengøring, produktion, tekstil
A30: Finansiel | B30: Er virksomhedens drift afhængig af adgang til vand i tilstrækkelig mængde og kvalitet? | C30: FALSE | D30: TRUE | E30: Gælder hvor vand er nødvendigt for driften – f.eks. i produktion, rengøring, køling, vanding eller ingredienser. Også relevant hvis forurening eller knaphed kan forstyrre produktionen. | F30: Produktion, landbrug, vaskerier, fødevarer, kemi
B31: Kan vandkvalitet eller forurening påvirke virksomhedens produkter, råvarer eller processer? | C31: TRUE | D31: FALSE | E31: Gælder f.eks. hvis produktkvalitet afhænger af rent vand (fødevarer, tekstiler), eller hvis råvarer bliver forurenet ved kontakt med vand. | F31: Fødevarer, tekstil, kemi, energi, metal
B32: Kan krav til vandforbrug eller spildevandshåndtering påvirke virksomhedens driftsomkostninger? | C32: FALSE | D32: TRUE | E32: Omfatter f.eks. spildevandsafgifter, investeringskrav i renseudstyr, målere, påbud, certificeringer eller miljøgodkendelser. | F32: Produktion, industri, landbrug, fødevare, byggeri
B33: Er virksomheden eller dens infrastruktur i risiko for havrelaterede klimaeffekter (oversvømmelse, stormflod, havspejl)? | C33: FALSE | D33: FALSE | E33: Gælder hvis lokationer, veje, leverandører eller anden kritisk drift er i lavtliggende eller kystnære områder med risiko for havstigning eller stormskader. | F33: Kystnær industri, havne, logistik, turisme, ejendomme
B34: Kan adgang til hav- eller vandressourcer blive begrænset af udtømning eller regulering og påvirke virksomhedens forsyning? | C34: FALSE | D34: TRUE | E34: Gælder hvis virksomheden er afhængig af ressourcer som fisk, sand, ferskvand, salt eller råstoffer fra havet, og disse kan blive begrænset af myndigheder eller miljøforhold. | F34: Fiskeri, byggeri, kemi, tekstil, fødevarer, eksport
A35: E4 | B35: Biodiversitet og økosystemer
A36: Impact | B36: Påvirker eller ændrer virksomheden arealer direkte gennem byggeri, produktion, landbrug mv. – eller indirekte gennem indflydelse på andres arealanvendelse? | C36: TRUE | D36: FALSE | E36: Dette gælder hvis virksomheden bygger nyt, anlægger infrastruktur, driver landbrug, skovbrug, råstofudvinding eller har indflydelse på andres arealanvendelse (f.eks. gennem rådgivning, investering eller produktkrav). Gælder også hvis virksomheden ejer grunde eller bygninger med betydelig udstrækning eller planlægger nybyggeri. | F36: Byggeri, landbrug, råstofudvinding, skovbrug, transport, ejendomsudvikling, rådgivning
B37: Bruger, sælger eller specificerer virksomheden naturressourcer som træ, fisk, sand, jord, grus eller landbrugsprodukter – direkte eller gennem værdikæden? | C37: FALSE | D37: TRUE | E37: Dækker fx brug, indkøb eller salg af materialer, fødevarer eller råvarer, der stammer fra naturen – f.eks. træ, fisk, mineraler, sand, grus, vand, jord eller landbrugsvarer. Gælder også hvis virksomheden indgår i værdikæder, hvor sådanne ressourcer udvindes. | F37: Landbrug, fødevare, byggeri, tekstil, handel, produktion, engros
B38: Har virksomhedens aktiviteter udledning eller påvirkning, som kan forringe naturen – f.eks. støj, lys, luftforurening eller udslip til jord og vand? | C38: TRUE | D38: FALSE | E38: Omfatter udledning af stoffer (f.eks. pesticider, næringsstoffer, kemikalier) eller forurening med støj, lys eller lugt, der påvirker dyreliv eller naturens balance. Gælder både direkte drift og transport, men ikke almindelig kontordrift. | F38: Byggeri, produktion, transport, events, landbrug, affald
B39: Håndterer, forarbejder eller sælger virksomheden produkter, der stammer fra levende organismer – f.eks. træ, planter, fødevarer eller dyr? | C39: TRUE | D39: FALSE | E39: Gælder hvis virksomheden beskæftiger sig med biologiske materialer – herunder fødevarer, trævarer, landbrugsprodukter, frø, blomster, husdyr eller fisk. | F39: Landbrug, fødevare, handel, træindustri, medicinal, detail
B40: Er der risiko for, at virksomhedens aktiviteter (f.eks. import, transport, jordarbejde) kan sprede invasive arter eller sygdomme i naturen? | C40: FALSE | D40: TRUE | E40: Omfatter risiko for spredning af arter eller sygdomme via transport, import, jordflytning, planter, dyr, emballage eller maskiner – også indirekte gennem leverandører eller kunder. | F40: Byggeri, transport, handel med planter/dyr, import, affald
A41: Finansiel | B41: Er virksomheden afhængig af naturressourcer, som kan blive udtømt eller forringet? | C41: FALSE | D41: TRUE | E41: Gælder hvis virksomheden er afhængig af adgang til f.eks. rent vand, frugtbar jord, bestemte fiskebestande, træsorter eller økosystemydelser (som bestøvning, naturlig vandrensning). | F41: Landbrug, fødevare, produktion, tekstil, medicinal
B42: Kan virksomhedens aktiviteter blive forsinket eller begrænset af regler om naturbeskyttelse eller habitatlovgivning? | C42: FALSE | D42: TRUE | E42: Dækker fx byggestop, krav til VVM-redegørelser, restriktioner i fredede eller beskyttede områder, eller hvis virksomheden skal indhente særlige tilladelser pga. påvirkning af biodiversitet. | F42: Byggeri, anlæg, vindmøller, råstofudvinding, transport
B43: Har virksomheden risiko for at blive forbundet med negativ påvirkning af biodiversitet eller natur? | C43: TRUE | D43: FALSE | E43: Gælder hvis virksomhedens aktiviteter (eller dens leverandørers) kan forbindes med rydning af skov, tab af levesteder, trussel mod arter eller nedbrydning af økosystemer. | F43: Fødevare, skovbrug, landbrug, byggeri, transport, tekstil
B44: Kan krav om naturgenopretning, kompensation eller biodiversitetsregnskaber påføre virksomheden ekstra omkostninger? | C44: FALSE | D44: TRUE | E44: Omfatter omkostninger til naturgenopretning, etablering af grønne områder, kompensation for indgreb, samt fremtidige krav om at dokumentere biodiversitetspåvirkning i regnskaber. | F44: Byggeri, råstofudvinding, kommuner, energiprojekter, infrastruktur
B45: Har virksomheden mulighed for at udvikle nye produkter eller tjenester baseret på naturbaserede løsninger eller fremme af biodiversitet? | C45: FALSE | D45: TRUE | E45: Dækker f.eks. løsninger til regnvandshåndtering, grønne tage, økologiske produkter, rådgivning i naturvenligt design eller investering i biodiversitet som forretningsmulighed. | F45: Byggeri, rådgivning, cleantech, fødevare, arkitektur, landskabsdesign
A46: E5 | B46: Ressourceanvendelse og cirkulær økonomi
A47: Impact | B47: Producerer eller forarbejder virksomheden fysiske produkter eller materialer? | C47: TRUE | D47: FALSE | E47: Gælder hvis virksomheden selv fremstiller eller bearbejder produkter, råvarer, halvfabrikata eller materialer – uanset skala. | F47: Produktion, byggeri, industri, fødevare, håndværk
B48: Producerer virksomheden affald ud over almindeligt kontoraffald fra ansatte? | C48: TRUE | D48: FALSE | E48: Gælder hvis virksomheden genererer produktionsaffald, emballage, organisk affald, byggeaffald eller lignende. | F48: Produktion, byggeri, fødevare, events, sundhed
B49: Har virksomheden direkte eller indirekte indflydelse på materialevalg i produkter og projekter? | C49: TRUE | D49: FALSE | E49: Gælder både ved direkte ansvar (produktion, design) og indirekte (rådgivning, kravspecifikation, indkøbspolitik). | F49: Produktion, byggeri, rådgivere, entreprenører, arkitekte
B50: Arbejder virksomheden i en branche med højt potentiale for genbrug, genanvendelse eller upcycling? | C50: TRUE | D50: FALSE | E50: Gælder f.eks. hvor store mængder materialer, emballage eller komponenter kan genbruges, recirkuleres eller upcycles. | F50: Byggeri, mode, produktion, møbler, elektronik
B51: Producerer, pakker eller handler virksomheden med produkter med emballage? | C51: TRUE | D51: FALSE | E51: Gælder både hvis man fremstiller, fylder eller sælger varer med emballage – også som underleverandør. | F51: Fødevare, handel, detail, kosmetik, produktion
A52: Finansiel | B52: Kan krav om øget affaldssortering, dokumentation eller genanvendelse påføre virksomheden ekstra omkostninger? | C52: TRUE | D52: FALSE | E52: Omfatter krav fra lovgivning eller kunder om sporbarhed, affaldshåndtering, genanvendelse eller miljøvenlige materialer. | F52: Byggeri, produktion, fødevare, transport, events
B53: Risikerer virksomheden at blive ramt af nye affaldsafgifter eller udvidet producentansvar? | C53: TRUE | D53: FALSE | E53: Gælder f.eks. plastafgifter, producentansvar for emballage eller elektronisk affald, samt ændringer i affaldslovgivning. | F53: Produktion, detail, engros, elektronik, fødevare
B54: Kan materialemangel eller udsving i råvarepriser påvirke virksomhedens økonomi eller forsyning? | C54: FALSE | D54: TRUE | E54: Gælder hvis virksomhedens drift afhænger af stabile priser eller adgang til bestemte materialer, råvarer eller komponenter. | F54: Produktion, byggeri, elektronik, tekstil, medicinal
B55: Har virksomheden mulighed for at opnå fordele gennem cirkulære løsninger, genbrug eller materialeeffektivitet? | C55: FALSE | D55: TRUE | E55: Gælder hvis virksomheden kan optimere indtjening, kundetilfredshed eller produktudvikling gennem cirkulære tiltag. | F55: Produktion, byggeri, cleantech, møbelindustri, fødevare
B56: Møder virksomheden krav fra kunder eller samarbejdspartnere om lavt ressourceforbrug eller affaldshåndtering? | C56: TRUE | D56: FALSE | E56: Omfatter krav i udbud, kontrakter, partnerskaber eller kundepræferencer – f.eks. ifm. grønne indkøb eller bæredygtighedscertificeringer. | F56: Leverandører, rådgivere, produktion, byggeri, engros
A57: S1 | B57: Egen arbejdsstyrke
A58: Impact | B58: Har virksomheden én eller flere ansatte – uanset om de er fuldtid, deltid eller midlertidige? | C58: TRUE | D58: FALSE | E58: Gælder alle typer ansatte i ind- og udland. Enkeltmandsvirksomheder uden ansatte kan svare nej. | F58: Alle
B59: Har nogen af virksomhedens ansatte opgaver, hvor efter- eller videreuddannelse er nødvendig for at opretholde kvalifikationer, sikkerhed eller lovkrav? | C59: TRUE | D59: FALSE | E59: F.eks. VVS’ere med krav om autorisation, faglærte med opkvalificering, ansatte i sundhed eller rådgivning, der skal være opdateret. | F59: Håndværk, rådgivning, sundhed, undervisning, transport, butik
B60: Har virksomheden ansatte, der arbejder i lande eller lokationer med høj risiko for brud på arbejdstagerrettigheder? Glæder også underfirmaer. | C60: FALSE | D60: TRUE | E60: F.eks. hvis ansatte arbejder i, eller virksomhed har produktion/samarbejde i lande som Kina, Bangladesh, Indien, Brasilien, Tyrkiet eller visse dele af Østeuropa og Afrika. | F60: Tekstil, produktion, landbrug, byggeri, handel
B61: Har virksomheden ansatte, der udfører fysisk arbejde med risiko for arbejdsskader? | C61: TRUE | D61: FALSE | E61: F.eks. arbejde med maskiner, tunge løft, fysisk belastning, håndtering af farlige stoffer, varme, støj eller kundekonflikter. | F61: Byggeri, håndværk, detail, industri, restauration
B62: Har virksomheden ansatte, der arbejder på skæve tidspunkter – f.eks. Aften, nat, tidlig morgen, aften eller weekender – som en del af den normale drift? | C62: TRUE | D62: FALSE | E62: Gælder hvis arbejdstiderne afviger fra almindelig kontortid som standard – ikke bare i særlige tilfælde. | F62: Hotel, restauration, transport, sundhed, rengøring, beredskab
A63: Finansiel | B63: Er virksomhedens drift afhængig af medarbejdere, hvor fravær (f.eks. ved sygdom, ulykker eller stress) kan påvirke produktion, service eller bemanding? | C63: TRUE | D63: FALSE | E63: Gælder hvis arbejdsopgaver ikke nemt kan varetages af andre – f.eks. pga. specialkompetencer, lav bemanding eller korte deadlines | F63: Produktion, sundhed, byggeri, detail, kontor
B64: Kan vanskeligheder med rekruttering, fastholdelse eller lav medarbejdertilfredshed føre til øgede omkostninger eller kapacitetsproblemer? | C64: TRUE | D64: FALSE | E64: Dækker f.eks. brancher med høj udskiftning, lav arbejdskrafttilgængelighed eller svag medarbejderloyalitet. | F64: It, byggeri, sundhed, detail, undervisning
B65: Er virksomheden aktiv i brancher eller områder, hvor attraktive løn- og arbejdsvilkår er afgørende for at tiltrække kvalificeret arbejdskraft? | C65: FALSE | D65: FALSE | E65: Gælder ved mangel på kvalificerede medarbejdere, eller hvor arbejdsvilkår er konkurrenceparameter. | F65: Teknik, sundhed, rådgivning, håndværk
B66: Kan lav medarbejdertrivsel, oplevet diskrimination eller manglende ligestilling udgøre en omdømmerisiko eller føre til tab af kunder? | C66: TRUE | D66: FALSE | E66: Gælder f.eks. hvis virksomheden er eksponeret i medier, arbejder med offentlige eller store kunder, eller har politikker på området. | F66: Offentlige leverandører, konsulenter, retail, tech
B67: Har virksomheden ansatte eller leverandører i brancher eller lande med kendt risiko for alvorlige brud på arbejdstagerrettigheder (f.eks. tvangsarbejde, børnearbejde)? | C67: FALSE | D67: FALSE | E67: Gælder især udenlandsk produktion, import eller outsourcing i højrisikosektorer og -lande, hvor virksomheden bærer ansvar i kæden. | F67: Tekstil, elektronik, byggeri, fødevarer, detail
A68: S2 | B68: Arbejdstagere i værdikæden
A69: Impact | B69: Har virksomheden leverandører eller underleverandører i lande eller brancher med svag beskyttelse af arbejdstagerrettigheder? | C69: TRUE | D69: FALSE | E69: Gælder samarbejde i højrisikoområder – f.eks. Bangladesh, Kina, Indien, Tyrkiet, Brasilien eller dele af Afrika og Østeuropa. | F69: Tekstil, elektronik, byggeri, detail, landbrug
B70: Benytter virksomheden andre virksomheder til regelmæssig drift – f.eks. uden fastansatte eller via outsourcing? | C70: FALSE | D70: TRUE | E70: Omfatter brug af rengøringsfirmaer, vikarer, selvstændige chauffører eller freelancere i daglig drift. | F70: Transport, rengøring, byggeri, service, events
B71: Udfører virksomhedens leverandører fysisk arbejde med risiko for arbejdsskader? | C71: TRUE | D71: FALSE | E71: F.eks. arbejde med maskiner, farlige stoffer, tunge løft, højder, varme eller kundekontakt. | F71: Produktion, byggeri, affald, handel, fødevarer
B72: Har virksomhedens krav – f.eks. lave priser, korte deadlines eller høj fleksibilitet – potentiel negativ indflydelse på arbejdsforhold i kæden? | C72: TRUE | D72: FALSE | E72: Gælder hvis virksomhedens krav indirekte kan føre til overarbejde, lav løn eller lav sikkerhed hos leverandører. | F72: Handel, mode, fødevarer, byggeprojekter
B73: Har virksomheden indflydelse på arbejdsforholdene hos centrale leverandører og underleverandører? | C73: TRUE | D73: FALSE | E73: F.eks. gennem audit, spørgeskemaer, due diligence eller krav om dokumentation. | F73: Tekstil, retail, produktion, fødevarer, industri
A74: Finansiel | B74: Er virksomheden afhængig af leverandører, hvor dårlige arbejdsvilkår kan føre til fejl, lav produktivitet, forsinkelser eller leveranceproblemer? | C74: TRUE | D74: FALSE | E74: Gælder hvor kvalitet, leveringstid eller kapacitet påvirkes af personaleforhold hos leverandøren. | F74: Produktion, elektronik, fødevarer, byggeri
B75: Risikerer virksomheden produktionsstop, kvalitetsproblemer eller leveranceforstyrrelser pga. dårlige arbejdsforhold i værdikæden? | C75: TRUE | D75: FALSE | E75: Dækker f.eks. højt fravær, lav bemanding, høj udskiftning eller manglende oplæring hos leverandører, som påvirker kvalitet og tid. | F75: Produktion, elektronik, byggeri, tekstil, fødevarer
B76: Har virksomheden begrænset indsigt i eller kontrol over arbejdsforholdene hos væsentlige underleverandører? | C76: FALSE | D76: FALSE | E76: Gælder især hvis der er mange led i kæden, brug af agenter, eller uklare kontrakter, hvor relationen er indirekte eller skifter ofte. | F76: Handel, tekstil, elektronik, transport, e-commerce
B77: Skal virksomheden dokumentere arbejdsforhold i værdikæden over for kunder, investorer eller myndigheder? | C77: FALSE | D77: TRUE | E77: F.eks. via CSRD, forsyningskædelove, krav i offentlige udbud eller partnerskabsaftaler. | F77: Rådgivning, produktion, detail, eksport
B78: Kan investering i bedre arbejdsforhold hos leverandører give økonomiske fordele – f.eks. lavere risiko, bedre kvalitet eller leveringssikkerhed? | C78: FALSE | D78: TRUE | E78: F.eks. gennem lavere udskiftning, færre fejl eller mere stabile relationer. | F78: Mode, byggeri, tech, detail, specialproduktion
A79: S3 | B79: Berørte samfund
A80: Impact | B80: Har virksomheden aktiviteter, projekter eller beslutninger, der fysisk påvirker lokalsamfund (f.eks. gennem støj, trafik, byggeri, udledning eller arealbrug)? | C80: TRUE | D80: FALSE | E80: Gælder både direkte og indirekte påvirkning – f.eks. via rådgivning, projektering eller udvikling. | F80: Rådgivning, byggeri, produktion, festivaler, events, infrastruktur
B81: Indgår virksomheden i projekter, hvor der bygges større anlæg, faciliteter eller infrastruktur tæt på beboelse eller følsomme områder? | C81: FALSE | D81: TRUE | E81: Gælder også hvis virksomheden er bygherre, lejer eller bestiller et anlæg. | F81: Ejendomsudvikling, industri, forsyning, logistik, sport, events
B82: Er virksomhedens aktiviteter placeret i eller tæt på lokalsamfund med høj følsomhed (f.eks. lav indkomst, sundhedsrisici, kulturel betydning eller oprindelige folk)? | C82: TRUE | D82: FALSE | E82: Der kan anvendes offentligt tilgængelige kortdata, lokal viden eller NGO-rapporter som vurderingsgrundlag. | F82: Råstofindvinding, landbrug, byggeri, produktion, energi
B83: Er virksomhedens drift afhængig af adgang til lokale naturressourcer som vand, landareal eller biodiversitet? | C83: FALSE | D83: FALSE | E83: Gælder både direkte brug og afledning – f.eks. forbrug af lokalt vand, adgangsveje, støjzoner. | F83: Landbrug, fødevarer, produktion, turisme
B84: Har virksomheden en betydelig fysisk tilstedeværelse i lokalområder (f.eks. fabrik, hotel, kontor eller butik), som giver mulighed for at støtte det lokale samfund? | C84: TRUE | D84: FALSE | E84: Gælder kun hvis virksomheden er fast til stede og har reelle muligheder – ikke symbolsk støtte. | F84: Industri, butik, hoteller, restauranter, pleje
A85: Finansiel | B85: Risikerer virksomheden modstand, klager eller forsinkelser fra lokalsamfund pga. dens aktiviteter, udbygning eller tilstedeværelse? | C85: TRUE | D85: FALSE | E85: F.eks. klager over støj, naboprotester, retssager, demonstrationer eller modstand mod byggeri. | F85: Infrastruktur, produktion, affald, råstof, logistik
B86: Kan ændringer i lokale forhold (f.eks. adgang til arbejdskraft, infrastruktur, politik eller regulering) påvirke virksomhedens drift? | C86: TRUE | D86: FALSE | E86: Gælder hvis virksomheden er afhængig af lokal kapacitet, adgangsforhold eller kommunal tilladelse. | F86: Forsyning, produktion, sundhed, byggeri, transport
B87: Er virksomheden afhængig af lokalt netværk (f.eks. vandforsyning, el, affald, transport), der kan være sårbart ved belastning eller nedbrud? | C87: FALSE | D87: TRUE | E87: Gælder særligt små samfund eller egne netværk, hvor systemet let overbelastes. | F87: Byggeri, festivaler, produktion, turisme
B88: Har virksomheden fysiske faciliteter i områder med høj risiko for naturkatastrofer, oversvømmelse eller klimarelaterede hændelser? | C88: FALSE | D88: TRUE | E88: Brug f.eks. nationale risikokort over oversvømmelse, skovbrand eller storme. | F88: Alle brancher med faste anlæg, især tæt på kyst eller lavtliggende områder
B89: Er virksomhedens aktiviteter afhængige af accept, samarbejde eller støtte fra lokale interessenter – f.eks. naboer, borgere, lokalt erhvervsliv eller kommune? | C89: TRUE | D89: FALSE | E89: Gælder især ved udvidelser, lokal synlighed eller CSR-indsats. | F89: Byggeri, rådgivning, events, butik, transport, infrastruktur
A90: S4 | B90: Forbrugere og slutbrugere
A91: Impact | B91: Har virksomheden direkte forbrugere eller slutbrugere af sine produkter eller ydelser? | C91: TRUE | D91: FALSE | E91: Gælder kun hvis slutbrugeren er den endelige bruger – ikke ved salg gennem mellemled uden kontakt til slutbrugeren. | F91: Fødevarer, detail, rådgivning til private, boligudlejning, sundhedsydelser
B92: Kan virksomhedens produkter eller ydelser påvirke sundhed, sikkerhed eller trivsel hos slutbrugeren? | C92: TRUE | D92: FALSE | E92: F.eks. tekniske løsninger, rådgivning, fødevarer, kemikalier eller byggeri, hvor fejl kan føre til skader eller helbredspåvirkninger. | F92: Byggeri, VVS, el, fødevarer, sundhed, kemi, rådgivning
B93: Kan fejl, svigt eller mangler i virksomhedens produkter eller ydelser føre til fysisk eller psykisk skade for slutbrugeren? | C93: TRUE | D93: FALSE | E93: Dækker f.eks. teknisk udstyr, rådgivning, byggematerialer, sikkerhedsprodukter eller medicin. | F93: Teknologi, byggeri, rådgivning, fødevarer, sundhed
B94: Er virksomhedens produkter eller ydelser rettet mod slutbrugere, der kan være særligt sårbare – f.eks. børn, ældre eller syge? | C94: TRUE | D94: FALSE | E94: Gælder hvis målgruppen eller en væsentlig del af slutbrugerne har behov for særlig beskyttelse. | F94: Sundhed, børneprodukter, ældrepleje, fødevarer, legetøj
B95: Når virksomhedens produkter eller ydelser frem til slutbrugeren uden at gå gennem andre virksomheder, der bearbejder, videresælger eller pakker dem? | C95: FALSE | D95: FALSE | E95: Gælder f.eks. direkte salg eller egne butikker, ikke hvis produktet går gennem grossister eller partnere, før det når forbrugeren. | F95: Fødevarer, detail, e-handel, rådgivning
A96: Finansiel | B96: Er virksomheden særlig eksponeret for offentlig kritik eller dårlig omtale, hvis dens produkter/ydelser har fejl, bivirkninger eller skader? | C96: TRUE | D96: FALSE | E96: Gælder særligt ved høj offentlig synlighed, følsomme produkter, eller produkter med sikkerheds- og sundhedsrisko. | F96: Rådgivning, byggeri, fødevarer, sundhed, tech
B97: Er virksomhedens slutbrugere afhængige af klare informationer, brugsanvisninger eller mærkning for at bruge produktet korrekt og sikkert? | C97: TRUE | D97: FALSE | E97: Gælder f.eks. fødevarer, medicin, kemikalier, teknisk udstyr eller digitale ydelser, hvor fejlbrug kan føre til skade. | F97: Fødevarer, medicin, elektronik, software
B98: Er der slutbrugere, hvis helbred, økonomi eller rettigheder kan påvirkes negativt, hvis produktet eller ydelsen ikke fungerer som forventet? | C98: TRUE | D98: FALSE | E98: Gælder f.eks. rådgivning, byggeri, sundhedsydelser eller forsikringer med stor betydning for slutbrugeren. | F98: Rådgivning, finans, byggeri, sundhed
B99: Kan ændringer i forbrugerpræferencer, f.eks. øget efterspørgsel på bæredygtige eller sikre produkter, påvirke virksomhedens konkurrenceevne? | C99: TRUE | D99: FALSE | E99: Gælder hvis forbrugerne forventer visse standarder – f.eks. økologi, sikkerhed, klima – som kan påvirke efterspørgslen. | F99: Fødevarer, tøj, tech, byggeri
B100: Kan virksomheden opnå økonomiske fordele (f.eks. nye markedsandele eller højere loyalitet) ved at tilbyde produkter med dokumenterede ESG-fordele? | C100: FALSE | D100: TRUE | E100: Gælder hvor der er en fordel ved at kommunikere om lav miljøpåvirkning, god etik, sikkerhed eller sundhed. | F100: Fødevarer, tekstil, tech, sundhed, energi
...

Sheet DVA
B1: impact | C1: Finansiel
A2: E1 | B2: =COUNTIF(DVA_Spørgsmål!C3:C7,TRUE) -> 2 | C2: =COUNTIF(DVA_Spørgsmål!C8:C12,TRUE) -> 1 | E2: Finansiel væsentlighed | F2: Meget høj | G2: {=_xlfn.TEXTJOIN(" ", TRUE, _xlfn._xlws.FILTER($A$2:$A$11, ($B$2:$B$11=0)*($C$2:$C$11=5),""))} | H2: {=_xlfn.TEXTJOIN(" ", TRUE, _xlfn._xlws.FILTER($A$2:$A$11, ($B$2:$B$11=1)*($C$2:$C$11=5),""))} | I2: {=_xlfn.TEXTJOIN(" ", TRUE, _xlfn._xlws.FILTER($A$2:$A$11, ($B$2:$B$11=2)*($C$2:$C$11=5),""))} | J2: {=_xlfn.TEXTJOIN(" ", TRUE, _xlfn._xlws.FILTER($A$2:$A$11, ($B$2:$B$11=3)*($C$2:$C$11=5),""))} | K2: {=_xlfn.TEXTJOIN(" ", TRUE, _xlfn._xlws.FILTER($A$2:$A$11, ($B$2:$B$11=4)*($C$2:$C$11=5),""))} | L2: {=_xlfn.TEXTJOIN(" ", TRUE, _xlfn._xlws.FILTER($A$2:$A$11, ($B$2:$B$11=5)*($C$2:$C$11=5),""))}
A3: E2 | B3: =COUNTIF(DVA_Spørgsmål!C14:C18,TRUE) -> 1 | C3: =COUNTIF(DVA_Spørgsmål!C19:C23,TRUE) -> 0 | F3: Høj | G3: {=_xlfn.TEXTJOIN(" ", TRUE, _xlfn._xlws.FILTER($A$2:$A$11, ($B$2:$B$11=0)*($C$2:$C$11=4),""))} | H3: {=_xlfn.TEXTJOIN(" ", TRUE, _xlfn._xlws.FILTER($A$2:$A$11, ($B$2:$B$11=1)*($C$2:$C$11=4),""))} | I3: {=_xlfn.TEXTJOIN(" ", TRUE, _xlfn._xlws.FILTER($A$2:$A$11, ($B$2:$B$11=2)*($C$2:$C$11=4),""))} | J3: {=_xlfn.TEXTJOIN(" ", TRUE, _xlfn._xlws.FILTER($A$2:$A$11, ($B$2:$B$11=3)*($C$2:$C$11=4),""))} | K3: {=_xlfn.TEXTJOIN(" ", TRUE, _xlfn._xlws.FILTER($A$2:$A$11, ($B$2:$B$11=4)*($C$2:$C$11=4),""))} -> S4 | L3: {=_xlfn.TEXTJOIN(" ", TRUE, _xlfn._xlws.FILTER($A$2:$A$11, ($B$2:$B$11=5)*($C$2:$C$11=4),""))}
A4: E3 | B4: =COUNTIF(DVA_Spørgsmål!C25:C29,TRUE) -> 1 | C4: =COUNTIF(DVA_Spørgsmål!C30:C34,TRUE) -> 1 | F4: Moderat | G4: {=_xlfn.TEXTJOIN(" ", TRUE, _xlfn._xlws.FILTER($A$2:$A$11, ($B$2:$B$11=0)*($C$2:$C$11=3),""))} | H4: {=_xlfn.TEXTJOIN(" ", TRUE, _xlfn._xlws.FILTER($A$2:$A$11, ($B$2:$B$11=1)*($C$2:$C$11=3),""))} | I4: {=_xlfn.TEXTJOIN(" ", TRUE, _xlfn._xlws.FILTER($A$2:$A$11, ($B$2:$B$11=2)*($C$2:$C$11=3),""))} | J4: {=_xlfn.TEXTJOIN(" ", TRUE, _xlfn._xlws.FILTER($A$2:$A$11, ($B$2:$B$11=3)*($C$2:$C$11=3),""))} -> S3 | K4: {=_xlfn.TEXTJOIN(" ", TRUE, _xlfn._xlws.FILTER($A$2:$A$11, ($B$2:$B$11=4)*($C$2:$C$11=3),""))} -> S1 | L4: {=_xlfn.TEXTJOIN(" ", TRUE, _xlfn._xlws.FILTER($A$2:$A$11, ($B$2:$B$11=5)*($C$2:$C$11=3),""))} -> E5
A5: E4 | B5: =COUNTIF(DVA_Spørgsmål!C36:C40,TRUE) -> 3 | C5: =COUNTIF(DVA_Spørgsmål!C41:C45,TRUE) -> 1 | F5: Middel | G5: {=_xlfn.TEXTJOIN(" ", TRUE, _xlfn._xlws.FILTER($A$2:$A$11, ($B$2:$B$11=0)*($C$2:$C$11=2),""))} | H5: {=_xlfn.TEXTJOIN(" ", TRUE, _xlfn._xlws.FILTER($A$2:$A$11, ($B$2:$B$11=1)*($C$2:$C$11=2),""))} | I5: {=_xlfn.TEXTJOIN(" ", TRUE, _xlfn._xlws.FILTER($A$2:$A$11, ($B$2:$B$11=2)*($C$2:$C$11=2),""))} | J5: {=_xlfn.TEXTJOIN(" ", TRUE, _xlfn._xlws.FILTER($A$2:$A$11, ($B$2:$B$11=3)*($C$2:$C$11=2),""))} -> G1 | K5: {=_xlfn.TEXTJOIN(" ", TRUE, _xlfn._xlws.FILTER($A$2:$A$11, ($B$2:$B$11=4)*($C$2:$C$11=2),""))} -> S2 | L5: {=_xlfn.TEXTJOIN(" ", TRUE, _xlfn._xlws.FILTER($A$2:$A$11, ($B$2:$B$11=5)*($C$2:$C$11=2),""))}
A6: E5 | B6: =COUNTIF(DVA_Spørgsmål!C47:C51,TRUE) -> 5 | C6: =COUNTIF(DVA_Spørgsmål!C52:C56,TRUE) -> 3 | F6: Lav | G6: {=_xlfn.TEXTJOIN(" ", TRUE, _xlfn._xlws.FILTER($A$2:$A$11, ($B$2:$B$11=0)*($C$2:$C$11=1),""))} | H6: {=_xlfn.TEXTJOIN(" ", TRUE, _xlfn._xlws.FILTER($A$2:$A$11, ($B$2:$B$11=1)*($C$2:$C$11=1),""))} -> E3 | I6: {=_xlfn.TEXTJOIN(" ", TRUE, _xlfn._xlws.FILTER($A$2:$A$11, ($B$2:$B$11=2)*($C$2:$C$11=1),""))} -> E1 | J6: {=_xlfn.TEXTJOIN(" ", TRUE, _xlfn._xlws.FILTER($A$2:$A$11, ($B$2:$B$11=3)*($C$2:$C$11=1),""))} -> E4 | K6: {=_xlfn.TEXTJOIN(" ", TRUE, _xlfn._xlws.FILTER($A$2:$A$11, ($B$2:$B$11=4)*($C$2:$C$11=1),""))} | L6: {=_xlfn.TEXTJOIN(" ", TRUE, _xlfn._xlws.FILTER($A$2:$A$11, ($B$2:$B$11=5)*($C$2:$C$11=1),""))}
A7: S1 | B7: =COUNTIF(DVA_Spørgsmål!C58:C62,TRUE) -> 4 | C7: =COUNTIF(DVA_Spørgsmål!C63:C67,TRUE) -> 3 | F7: Ikke relevant | G7: {=_xlfn.TEXTJOIN(" ", TRUE, _xlfn._xlws.FILTER($A$2:$A$11, ($B$2:$B$11=0)*($C$2:$C$11=0),""))} | H7: {=_xlfn.TEXTJOIN(" ", TRUE, _xlfn._xlws.FILTER($A$2:$A$11, ($B$2:$B$11=1)*($C$2:$C$11=0),""))} -> E2 | I7: {=_xlfn.TEXTJOIN(" ", TRUE, _xlfn._xlws.FILTER($A$2:$A$11, ($B$2:$B$11=2)*($C$2:$C$11=0),""))} | J7: {=_xlfn.TEXTJOIN(" ", TRUE, _xlfn._xlws.FILTER($A$2:$A$11, ($B$2:$B$11=3)*($C$2:$C$11=0),""))} | K7: {=_xlfn.TEXTJOIN(" ", TRUE, _xlfn._xlws.FILTER($A$2:$A$11, ($B$2:$B$11=4)*($C$2:$C$11=0),""))} | L7: {=_xlfn.TEXTJOIN(" ", TRUE, _xlfn._xlws.FILTER($A$2:$A$11, ($B$2:$B$11=5)*($C$2:$C$11=0),""))}
A8: S2 | B8: =COUNTIF(DVA_Spørgsmål!C69:C73,TRUE) -> 4 | C8: =COUNTIF(DVA_Spørgsmål!C74:C78,TRUE) -> 2 | G8: Ikke relevant | H8: Lav | I8: Middel | J8: Moderat | K8: Høj | L8: Meget høj
A9: S3 | B9: =COUNTIF(DVA_Spørgsmål!C80:C84,TRUE) -> 3 | C9: =COUNTIF(DVA_Spørgsmål!C85:C89,TRUE) -> 3 | G9: Impact væsentlighed
A10: S4 | B10: =COUNTIF(DVA_Spørgsmål!C91:C95,TRUE) -> 4 | C10: =COUNTIF(DVA_Spørgsmål!C96:C100,TRUE) -> 4
A11: G1 | B11: =COUNTIF(DVA_Spørgsmål!C102:C106,TRUE) -> 3 | C11: =COUNTIF(DVA_Spørgsmål!C107:C111,TRUE) -> 2
D29: {=_xlfn.TEXTJOIN(" ",,IF(AND(B2:B11=0,C2:C11=0),A2:A11,E29))}

Sheet Matrix
A1: Kriterium | B1: Indikator | E1: Indikator point | F1: Afkrydsningsfelt | G1: Samlet indikator point | H1: Max Point | I1: Score | J1: Max Score | K1: Gruppevægtning | L1: Hoved-Dokumentation | M1: Kommentarer / Bemærkninger
A2: E1 | B2: Klimaforandringer | G2: =SUM(G4:G25) -> 100 | H2: 100 | I2: =G2*J2/100 -> 5 | J2: =Forside!C2/SUM(Forside!C2:C6)*Matrix!K2*100 -> 5 | K2: 0.4
B3: 1.1 | C3: CO2 udledninger
C4: 1.1.1 | D4: Virksomheden har udregnet og dokumenteret sine CO2e-udledninger for Scope 1 og 2. | E4: 10 | F4: TRUE | G4: =SUMIF(F4:F8,TRUE,E4:E8) -> 35 | H4: 35 | I4: =IF(F4=TRUE,E4*$J$2,0)/100 -> 0.5 | L4: CO2e-beregning opdelt i scope 1 og 2.
C5: 1.1.2 | D5: Virksomheden har udregnet og dokumenteret sine CO2e-udledninger for Scope 1, 2 og 3. | E5: 5 | F5: TRUE | I5: =IF(F5=TRUE,E5*$J$2,0)/100 -> 0.25 | L5: CO2e-beregning opdelt i scope 1, 2 og 3.
C6: 1.1.3 | D6: Virksomheden har en politik for reduktion af sine CO2e-udledninger. | E6: 5 | F6: TRUE | I6: =IF(F6=TRUE,E6*$J$2,0)/100 -> 0.25 | L6: Nedskreven politik.
C7: 1.1.4 | D7: Virksomheden har konkrete mål for reduktion af sine CO2e-udledninger. | E7: 5 | F7: TRUE | I7: =IF(F7=TRUE,E7*$J$2,0)/100 -> 0.25 | L7: Nedskrevne mål med tidsramme.
C8: 1.1.5 | D8: Virksomheden har en strategi for, hvordan de vil opnå deres CO2e-reduktionsmål. | E8: 10 | F8: TRUE | I8: =IF(F8=TRUE,E8*$J$2,0)/100 -> 0.5 | L8: Nedskreven strategi.
B9: 1.2 | C9: Energiledelse og energiforbrug
C10: 1.2.1 | D10: Virksomheden har udpeget ansvarlige for energiledelse og fastlagt, hvordan ansvaret er organiseret på den pågældende lokation. | E10: 10 | F10: TRUE | G10: =SUMIF(F10:F14,TRUE,E10:E14) -> 35 | H10: 35 | I10: =IF(F10=TRUE,E10*$J$2,0)/100 -> 0.5 | L10: Samlet overblik over energiforbrug fordelt på energikilder.
C11: 1.2.2 | D11: Virksomheden har en politik for at håndtere energiforbrug og energimiks. | E11: 5 | F11: TRUE | I11: =IF(F11=TRUE,E11*$J$2,0)/100 -> 0.25 | L11: Nedskreven politik.
C12: 1.2.3 | D12: Virksomheden har konkrete målsætninger for at øge andelen af vedvarende energi og reducere energiforbruget. | E12: 5 | F12: TRUE | I12: =IF(F12=TRUE,E12*$J$2,0)/100 -> 0.25 | L12: Nedskrevne mål med tidsramme.
C13: 1.2.4 | D13: Virksomheden har en handlingsplan/strategi for, hvordan de vil opnå deres energimål. | E13: 10 | F13: TRUE | I13: =IF(F13=TRUE,E13*$J$2,0)/100 -> 0.5 | L13: Nedskreven strategi.
C14: 1.2.5 | D14: Virksomheden overvåger systematisk og følger op på sit energiforbrug | E14: 5 | F14: TRUE | I14: =IF(F14=TRUE,E14*$J$2,0)/100 -> 0.25
B15: 1.3 | C15: Vedvarende energi
C16: 1.3.1 | D16: Mindst 20% af virksomhedens energiforbrug stammer fra vedvarende energikilder | E16: 2.5 | F16: TRUE | G16: =SUMIF(F16:F19,TRUE,E16:E19) -> 15 | H16: 15 | I16: =IF(F16=TRUE,E16*$J$2,0)/100 -> 0.125
C17: 1.3.2 | D17: Mindst 50% af virksomhedens energiforbrug stammer fra vedvarende energikilder | E17: 2.5 | F17: TRUE | I17: =IF(F17=TRUE,E17*$J$2,0)/100 -> 0.125
C18: 1.3.3 | D18: Hele virksomhedens energiforbrug stammer fra vedvarende energikilder | E18: 5 | F18: TRUE | I18: =IF(F18=TRUE,E18*$J$2,0)/100 -> 0.25
C19: 1.3.4 | D19: Virksomheden kan dokumentere oprindelsen af den energi, som hævdes at være grøn, uanset andel. | E19: 5 | F19: TRUE | I19: =IF(F19=TRUE,E19*$J$2,0)/100 -> 0.25
B20: 1.4 | C20: Energimærke
C21: 1.4.1 | D21: Virksomheden har dokumenteret energimærkningen af størstedelen af sine bygninger. | E21: 5 | F21: TRUE | G21: =SUMIF(F21:F25,TRUE,E21:E25) -> 15 | H21: 15 | I21: =IF(F21=TRUE,E21*$J$2,0)/100 -> 0.25 | L21: Kopi af/link til gyldigt energimærke
C22: 1.4.2 | D22: Størstedelen af virksomhedens bygninger har energimærke B eller bedre. | E22: 2 | F22: TRUE | I22: =IF(F22=TRUE,E22*$J$2,0)/100 -> 0.1 | L22: Kopi af/link til gyldige energimærker og opvarmet etagearealer. Eller kriterie 1.3.3.
C23: 1.4.3 | D23: Størstedelen af virksomhedens bygninger har energimærke A2010 eller bedre. | E23: 2 | F23: TRUE | I23: =IF(F23=TRUE,E23*$J$2,0)/100 -> 0.1 | L23: Kopi af/link til gyldige energimærker og opvarmet etagearealer. Eller kriterie 1.3.4.
C24: 1.4.4 | D24: Størstedelen af virksomhedens bygninger har energimærke A2015 eller bedre. | E24: 2 | F24: TRUE | I24: =IF(F24=TRUE,E24*$J$2,0)/100 -> 0.1 | L24: Kopi af/link til gyldige energimærker og opvarmet etagearealer. Eller kriterie 1.3.5.
C25: 1.4.5 | D25: Størstedelen af virksomhedens bygninger har energimærke A2020. | E25: 4 | F25: TRUE | I25: =IF(F25=TRUE,E25*$J$2,0)/100 -> 0.2 | L25: Kopi af/link til gyldige energimærker og opvarmet etagearealer. Eller kriterie 1.3.3
A26: E2 | B26: Forurening | G26: =SUM(G27:G50) -> 100 | H26: 100 | I26: =G26*J26/100 -> 0 | J26: =Forside!C3/SUM(Forside!C2:C6)*Matrix!K2*100 -> 0
B27: 2.1 | C27: Kortlægning og strategi for forurening
C28: 2.1.1 | D28: Virksomheden har taget stilling til, hvor den har risiko for at bidrage til miljøforurening. | E28: 15 | F28: TRUE | G28: =SUMIF(F28:F31,TRUE,E28:E31) -> 40 | H28: 40 | I28: =IF(F28=TRUE,E28*$J$26,0)/100 -> 0 | L28: Vurdering i form af rapport eller lign.
C29: 2.1.2 | D29: Virksomheden har en politik for forurening. | E29: 10 | F29: TRUE | I29: =IF(F29=TRUE,E29*$J$26,0)/100 -> 0 | L29: Nedskreven politik.
C30: 2.1.3 | D30: Virksomheden har konkrete mål for reduktion af deres forurening. | E30: 5 | F30: TRUE | I30: =IF(F30=TRUE,E30*$J$26,0)/100 -> 0 | L30: Nedskrevne mål med tidsramme.
C31: 2.1.4 | D31: Virksomheden har en handlingsplan/strategi for, hvordan de vil opnå deres mål om mindre forurening. | E31: 10 | F31: TRUE | I31: =IF(F31=TRUE,E31*$J$26,0)/100 -> 0 | L31: Nedskreven strategi.
B32: 2.2 | C32: Luftforurening
C33: 2.2.1 | D33: Virksomheden registrerer og rapporterer sine NOX-, SO2- og partikeludledninger. | E33: 2.5 | F33: TRUE | G33: =SUMIF(F33:F36,TRUE,E33:E36) -> 10 | H33: 10 | I33: =IF(F33=TRUE,E33*$J$26,0)/100 -> 0
C34: 2.2.2 | D34: Virksomheden har målsætninger for reduktion af disse emissioner inden for 3 år. | E34: 2.5 | F34: TRUE | I34: =IF(F34=TRUE,E34*$J$26,0)/100 -> 0
C35: 2.2.3 | D35: Halvdelen af virksomhedens transport er emissionsfri. | E35: 2.5 | F35: TRUE | I35: =IF(F35=TRUE,E35*$J$26,0)/100 -> 0
C36: 2.2.4 | D36: Over 90% af virksomhedens transport er emissionsfri. | E36: 2.5 | F36: TRUE | I36: =IF(F36=TRUE,E36*$J$26,0)/100 -> 0
B37: 2.3 | C37: Vandforurening
C38: 2.3.1 | D38: Virksomheden har dokumenteret spildevandshåndtering, inkl. Rensning. | E38: 5 | F38: TRUE | G38: =SUMIF(F38:F40,TRUE,E38:E40) -> 10 | H38: 10 | I38: =IF(F38=TRUE,E38*$J$26,0)/100 -> 0
C39: 2.3.2 | D39: Halvdelen af virksomhedens spildevand renses før det ledes til kloak/natur. | E39: 2.5 | F39: TRUE | I39: =IF(F39=TRUE,E39*$J$26,0)/100 -> 0
C40: 2.3.3 | D40: Hele virksomhedens spildevand renses før det ledes til kloak/natur. | E40: 2.5 | F40: TRUE | I40: =IF(F40=TRUE,E40*$J$26,0)/100 -> 0
B41: 2.4 | C41: Jordbundsforurening
C42: 2.4.1 | D42: Virksomheden opbevarer alle potentielt forurenende stoffer på forsvarlig vis. | E42: 5 | F42: TRUE | G42: =SUMIF(F42:F43,TRUE,E42:E43) -> 10 | H42: 10 | I42: =IF(F42=TRUE,E42*$J$26,0)/100 -> 0
C43: 2.4.2 | D43: Virksomheden har en plan for spildhåndtering og nødberedskab ved udslip. | E43: 5 | F43: TRUE | I43: =IF(F43=TRUE,E43*$J$26,0)/100 -> 0
B44: 2.5 | C44: Forurening af levende organismer og fødevareressourcer
C45: 2.5.1 | D45: Virksomheden har målsætninger for udfasning af skadelige stoffer eller praksisser med negativ indvirkning på biodiversitet. | E45: 10 | F45: TRUE | G45: =SUMIF(F45:F45,TRUE,E45:E45) -> 10 | H45: 10 | I45: =IF(F45=TRUE,E45*$J$26,0)/100 -> 0
B46: 2.6 | C46: Problematiske og særligt problematiske stoffer
C47: 2.6.1 | D47: Virksomheden har en liste over anvendte kemikalier og har identificeret stoffer, der er omfattet af REACH og SVCH. | E47: 5 | F47: TRUE | G47: =SUMIF(F47:F48,TRUE,E47:E48) -> 10 | H47: 10 | I47: =IF(F47=TRUE,E47*$J$26,0)/100 -> 0
C48: 2.6.2 | D48: Over 90% af virksomhedens anvendte stoffer er klassificeret som ufarlige eller lavrisiko. | E48: 5 | F48: TRUE | I48: =IF(F48=TRUE,E48*$J$26,0)/100 -> 0
B49: 2.7 | C49: Mikroplast
C50: 2.7.1 | D50: Virksomheden har teknologier eller metoder til at minimere mikroplast. | E50: 10 | F50: TRUE | G50: =SUMIF(F50,TRUE,E50) -> 10 | H50: 10 | I50: =IF(F50=TRUE,E50*$J$26,0)/100 -> 0
A51: E3 | B51: Vand- og havressourcer | G51: =SUM(G52:G56) -> 100 | H51: 100 | I51: =G51*J51/100 -> 5 | J51: =Forside!C4/SUM(Forside!C2:C6)*Matrix!K2*100 -> 5
B52: 3.1 | C52: Vandforbrug og vandudtag
C53: 3.1.1 | D53: Virksomheden har dokumenteret sit vandforbrug og vandudtag. | E53: 15 | F53: TRUE | G53: =SUMIF(F53:F56,TRUE,E53:E56) -> 100 | H53: 100 | I53: =IF(F53=TRUE,E53*$J$51,0)/100 -> 0.75
C54: 3.1.2 | D54: Virksomheden har en politik for vandforbrug. | E54: 40 | F54: TRUE | I54: =IF(F54=TRUE,E54*$J$51,0)/100 -> 2
C55: 3.1.3 | D55: Virksomheden har konkrete mål for reduktion af vandudtag og vandforbrug. | E55: 15 | F55: TRUE | I55: =IF(F55=TRUE,E55*$J$51,0)/100 -> 0.75
C56: 3.1.4 | D56: Virksomheden har en handlingsplan/strategi for, hvordan de vil opnå deres vandreduktionsmål. | E56: 30 | F56: TRUE | I56: =IF(F56=TRUE,E56*$J$51,0)/100 -> 1.5
A57: E4 | B57: Biodiversitet og økosystemer | G57: =SUM(G58:G69) -> 0 | H57: 100 | I57: =G57*J57/100 -> 0 | J57: =Forside!C5/SUM(Forside!C2:C6)*Matrix!K2*100 -> 10
B58: 4.1 | C58: Arealforbrug
C59: 4.1.1 | D59: Virksomheden har dokumenteret det samlede arealforbrug, herunder andele af befæstet areal og naturbaserede arealer, både på og uden for virksomhedens matrikel. | E59: 5 | F59: FALSE | G59: =SUMIF(F59:F61,TRUE,E59:E61) -> 0 | H59: 20 | I59: =IF(F59=TRUE,E59*$J$57,0)/100 -> 0
C60: 4.1.2 | D60: Virksomheden har identificeret, om den opererer i eller tæt på biodiversitetsfølsomme områder, og i så fald angivet hvilke og hvor stort et areal der er påvirket. | E60: 5 | F60: FALSE | I60: =IF(F60=TRUE,E60*$J$57,0)/100 -> 0
C61: 4.1.3 | D61: Virksomheden arbejder aktivt for at minimere negativ arealpåvirkning, fx ved grønne tage, regn bede, ubefæstede områder eller naturgenopretning. | E61: 10 | F61: FALSE | I61: =IF(F61=TRUE,E61*$J$57,0)/100 -> 0
B62: 4.2 | C62: Indvirkning på biodiversitet og økosystemtjenester
C63: 4.2.1 | D63: Virksomheden har vurderet sin påvirkning på biodiversitet gennem f.eks. lys, støj, forurening, invasive arter eller kemikalier. | E63: 10 | F63: FALSE | G63: =SUMIF(F63:F65,TRUE,E63:E65) -> 0 | H63: 30 | I63: =IF(F63=TRUE,E63*$J$57,0)/100 -> 0
C64: 4.2.2 | D64: Virksomheden bidrager til at beskytte eller forbedre lokal biodiversitet gennem konkrete tiltag som fx beplantning af hjemmehørende arter, levesteder for insekter og fugle, eller partnerskaber med naturorganisationer. | E64: 10 | F64: FALSE | I64: =IF(F64=TRUE,E64*$J$57,0)/100 -> 0
C65: 4.2.3 | D65: Virksomheden har vurderet, om dens aktiviteter påvirker truede arter eller økosystemtjenester (fx bestøvning, rensning af luft/vand) og dokumenteret eventuelle indsatser. | E65: 10 | F65: FALSE | I65: =IF(F65=TRUE,E65*$J$57,0)/100 -> 0
B66: 4.3 | C66: Strategi og dokumentation
C67: 4.3.1 | D67: Virksomheden har en politik for biodiversitet, som tager hensyn til biodiversiteten og økosystemerne som virksomheden påvirker. | E67: 20 | F67: FALSE | G67: =SUMIF(F67:F69,TRUE,E67:E69) -> 0 | H67: 50 | I67: =IF(F67=TRUE,E67*$J$57,0)/100 -> 0
C68: 4.3.2 | D68: Virksomheden har konkrete målsætninger for biodiversitet. | E68: 10 | F68: FALSE | I68: =IF(F68=TRUE,E68*$J$57,0)/100 -> 0
C69: 4.3.3 | D69: Virksomheden har en handlingsplan/strategi for at opnå disse mål. | E69: 20 | F69: FALSE | I69: =IF(F69=TRUE,E69*$J$57,0)/100 -> 0
A70: E5 | B70: Ressourceanvendelse og cirkulær økonomi | G70: =SUM(G71:G80) -> 0 | H70: 100 | I70: =G70*J70/100 -> 0 | J70: =Forside!C6/SUM(Forside!C2:C6)*Matrix!K2*100 -> 20
B71: 5.1 | C71: Cirkulær økonomi
C72: 5.1.1 | D72: Virksomheden har en politik for ressourceanvendelse og cirkulær økonomi. | E72: 20 | F72: FALSE | G72: =SUMIF(F72:F74,TRUE,E72:E74) -> 0 | H72: 50 | I72: =IF(F72=TRUE,E72*$J$70,0)/100 -> 0
C73: 5.1.2 | D73: Virksomheden har konkrete mål for at forbedre ressourceeffektivitet og cirkulær økonomi. | E73: 10 | F73: FALSE | I73: =IF(F73=TRUE,E73*$J$70,0)/100 -> 0
C74: 5.1.3 | D74: Virksomheden har en handlingsplan/strategi for at opnå disse mål. | E74: 20 | F74: FALSE | I74: =IF(F74=TRUE,E74*$J$70,0)/100 -> 0
B75: 5.2 | C75: Affaldshåndtering
C76: 5.2.1 | D76: Virksomheden har dokumenteret sin samlede årlige affaldsmængde. | E76: 15 | F76: FALSE | G76: =SUMIF(F76:F80,TRUE,E76:E80) -> 0 | H76: 50 | I76: =IF(F76=TRUE,E76*$J$70,0)/100 -> 0
C77: 5.2.2 | D77: Hvis virksomheden arbejder i en materialetung sektor, har den dokumenteret mængden af forskellige materialetyper i ton/m³. | E77: 10 | F77: FALSE | I77: =IF(F77=TRUE,E77*$J$70,0)/100 -> 0
C78: 5.2.3 | D78: Virksomheden har en politik for affaldshåndtering. | E78: 10 | F78: FALSE | I78: =IF(F78=TRUE,E78*$J$70,0)/100 -> 0
C79: 5.2.4 | D79: Virksomheden har konkrete mål for at reducere affaldsmængden og øge genbrug/genanvendelse. | E79: 5 | F79: FALSE | I79: =IF(F79=TRUE,E79*$J$70,0)/100 -> 0
C80: 5.2.5 | D80: Virksomheden har en handlingsplan/strategi for at opnå disse mål. | E80: 10 | F80: FALSE | I80: =IF(F80=TRUE,E80*$J$70,0)/100 -> 0
A81: S1 | B81: Egen arbejdsstyrke | G81: =SUM(G82:G108) -> 65 | H81: 100 | I81: =G81*J81/100 -> 4.5 | J81: =Forside!C7/SUM(Forside!C7:C10)*Matrix!K81*100 -> 6.9230769 | K81: 0.3
B82: 1.1 | C82: Arbejdsulykker
C83: 1.1.1 | D83: Virksomheden har dokumenteret antallet af arbejdsulykker og deres frekvens. | E83: 5 | F83: TRUE | G83: =SUMIF(F83:F85,TRUE,E83:E85) -> 20 | H83: 20 | I83: =IF(F83=TRUE,E83*$J$81,0)/100 -> 0.34615385
C84: 1.1.2 | D84: Virksomheden har en politik for sundhed og sikkerhed, der sigter mod at forebygge arbejdsulykker. | E84: 10 | F84: TRUE | I84: =IF(F84=TRUE,E84*$J$81,0)/100 -> 0.69230769
C85: 1.1.3 | D85: Virksomheden har registreret arbejdsrelaterede dødsfald og arbejder på at reducere sådanne hændelser. | E85: 5 | F85: TRUE | I85: =IF(F85=TRUE,E85*$J$81,0)/100 -> 0.34615385
B86: 1.2 | C86: Vederlag og overenskomster
C87: 1.2.1 | D87: Virksomheden sikrer, at alle ansatte modtager en løn, der lever op til lovgivning eller overenskomster. | E87: 5 | F87: TRUE | G87: =SUMIF(F87:F90,TRUE,E87:E90) -> 10 | H87: 20 | I87: =IF(F87=TRUE,E87*$J$81,0)/100 -> 0.34615385
C88: 1.2.2 | D88: Virksomheden har dokumenteret lønforskellen mellem mandlige og kvindelige ansatte, hvis relevant. | E88: 5 | F88: FALSE | I88: =IF(F88=TRUE,E88*$J$81,0)/100 -> 0
C89: 1.2.3 | D89: Virksomheden har en strategi for lønstruktur og ansættelsesvilkår. | E89: 5 | F89: TRUE | I89: =IF(F89=TRUE,E89*$J$81,0)/100 -> 0.34615385
C90: 1.2.4 | D90: Virksomheden har angivet procentdelen af medarbejderne er dækket af kollektive overenskomster. | E90: 5 | F90: FALSE | I90: =IF(F90=TRUE,E90*$J$81,0)/100 -> 0
B91: 1.3 | C91: Uddannelse
C92: 1.3.1 | D92: Virksomheden tilbyder uddannelse til sine ansatte og har dokumenteret uddannelsestimer pr. ansat. | E92: 5 | F92: TRUE | G92: =SUMIF(F92:F94,TRUE,E92:E94) -> 5 | H92: 15 | I92: =IF(F92=TRUE,E92*$J$81,0)/100 -> 0.34615385
C93: 1.3.2 | D93: Uddannelsestimerne er opdelt efter køn og relevante medarbejdergrupper. | E93: 5 | F93: FALSE | I93: =IF(F93=TRUE,E93*$J$81,0)/100 -> 0
C94: 1.3.3 | D94: Virksomheden har en strategi for medarbejderudvikling og kompetenceopbygning. | E94: 5 | F94: FALSE | I94: =IF(F94=TRUE,E94*$J$81,0)/100 -> 0
B95: 1.4 | C95: Menneskerettigheder og etiske retningslinjer
C96: 1.4.1 | D96: Virksomheden har en Code of Conduct eller en menneskerettighedspolitik, der dækker nøgleområder som børnearbejde, tvangsarbejde og diskrimination. | E96: 5 | F96: FALSE | G96: =SUMIF(F96:F98,TRUE,E96:E98) -> 10 | H96: 15 | I96: =IF(F96=TRUE,E96*$J$81,0)/100 -> 0
C97: 1.4.2 | D97: Virksomheden har en strategi for at håndtere medarbejderklager og sikre et etisk arbejdsmiljø. | E97: 5 | F97: TRUE | I97: =IF(F97=TRUE,E97*$J$81,0)/100 -> 0.34615385
C98: 1.4.3 | D98: Virksomheden har tidligere håndteret hændelser relateret til menneskerettigheder og har dokumenteret de skridt, der blev taget. | E98: 5 | F98: TRUE | I98: =IF(F98=TRUE,E98*$J$81,0)/100 -> 0.34615385
B99: 1.5 | C99: Demografiske data
C100: 1.5.1 | D100: Virksomheden har dokumenteret antal ansatte og opdelingen mellem midlertidige og fastansatte. | E100: 2.5 | F100: TRUE | G100: =SUMIF(F100:F103,TRUE,E100:E103) -> 10 | H100: 10 | I100: =IF(F100=TRUE,E100*$J$81,0)/100 -> 0.17307692
...

Sheet Branchekoder
B1: Branchekode | C1: Titel på branchekode | D1: Beskrivelse
A2: =B2 & " " & C2 -> 01.11.00 Dyrkning af korn (undtagen ris), bælgfrugter og olieholdige frø | B2: 01.11.00 | C2: Dyrkning af korn (undtagen ris), bælgfrugter og olieholdige frø | D2: Branchen omfatter dyrkning af alle former for korn (undtagen ris), herunder pseudo-korn (fx quinoa), bælgfrugter og olieholdige frø.
A3: =B3 & " " & C3 -> 01.12.00 Dyrkning af ris | B3: 01.12.00 | C3: Dyrkning af ris | D3: Branchen omfatter dyrkning af ris.
A4: =B4 & " " & C4 -> 01.13.00 Dyrkning af grøntsager og meloner, rødder og rodknolde | B4: 01.13.00 | C4: Dyrkning af grøntsager og meloner, rødder og rodknolde | D4: Branchen omfatter dyrkning af grøntsager og meloner, rødder og rodknolde, fx agurker, tomater, kartofler, maniok og honningmeloner.
A5: =B5 & " " & C5 | D5: Dyrkning af krydderiplanter og aromaplanter henvises til 01.28.00.
A6: =B6 & " " & C6 -> 01.14.00 Dyrkning af sukkerrør | B6: 01.14.00 | C6: Dyrkning af sukkerrør | D6: Branchen omfatter dyrkning af sukkerrør.
A7: =B7 & " " & C7 | D7: Dyrkning af sukkerroer henvises til 01.13.00.
A8: =B8 & " " & C8 -> 01.15.00 Dyrkning af tobak | B8: 01.15.00 | C8: Dyrkning af tobak | D8: Branchen omfatter dyrkning og den indledende forarbejdning af råtobak.
A9: =B9 & " " & C9 -> 01.16.00 Dyrkning af tekstilplanter | B9: 01.16.00 | C9: Dyrkning af tekstilplanter | D9: Branchen omfatter dyrkning af tekstilplanter, fx bomuld, jute, hør og hamp.
A10: =B10 & " " & C10 -> 01.19.00 Dyrkning af andre etårige afgrøder | B10: 01.19.00 | C10: Dyrkning af andre etårige afgrøder | D10: Branchen omfatter dyrkning af etårige afgrøder, fx foderafgrøder, roefrø og frø fra foderplanter samt dyrkning og fremstilling af blomster, afskårne blomster, blomsterknopper og blomsterfrø.
A11: =B11 & " " & C11 -> 01.21.00 Dyrkning af druer | B11: 01.21.00 | C11: Dyrkning af druer | D11: Branchen omfatter dyrkning af druer, fx druer til presning og spisning.
A12: =B12 & " " & C12
A13: =B13 & " " & C13 | D13: Fremstilling af vin henvises til 11.02.00.
A14: =B14 & " " & C14 -> 01.22.00 Dyrkning af tropiske og subtropiske frugter | B14: 01.22.00 | C14: Dyrkning af tropiske og subtropiske frugter | D14: Branchen omfatter dyrkning af tropiske og subtropiske frugter, fx avocado, ananas, bananer, dadler, figner, mango og papaya.
A15: =B15 & " " & C15 -> 01.23.00 Dyrkning af citrusfrugter | B15: 01.23.00 | C15: Dyrkning af citrusfrugter | D15: Branchen omfatter dyrkning af citrusfrugter, fx grapefrugt, citron, lime og appelsiner.
A16: =B16 & " " & C16 -> 01.24.00 Dyrkning af kernefrugter og stenfrugter | B16: 01.24.00 | C16: Dyrkning af kernefrugter og stenfrugter | D16: Branchen omfatter dyrkning af frugter med sten eller kerner som fx æbler, pærer, kvæder, abrikoser, kirsebær, ferskner, blommer og slåen.
A17: =B17 & " " & C17 -> 01.25.00 Dyrkning af andre træfrugter, bær og nødder | B17: 01.25.00 | C17: Dyrkning af andre træfrugter, bær og nødder | D17: Branchen omfatter dyrkning af andre træfrugter, bær og nødder, fx blåbær, ribs, solbær, stikkelsbær, hindbær, jordbær og kiwifrugter.
A18: =B18 & " " & C18
A19: =B19 & " " & C19 | D19: Branchen omfatter også dyrkning af frugtfrø samt dyrkning af spiselige nødder, bortset fra kokosnødder, som henvises til 01.26.00.
A20: =B20 & " " & C20 -> 01.26.00 Dyrkning af olieholdige frugter | B20: 01.26.00 | C20: Dyrkning af olieholdige frugter | D20: Branchen omfatter dyrkning af olieholdige frugter, fx kokosnødder, oliven og olieplanter.
A21: =B21 & " " & C21
A22: =B22 & " " & C22 | D22: Dyrkning af sojabønner, jordnødder og andre olieholdige frø henvises til 01.11.00.
A23: =B23 & " " & C23 -> 01.27.00 Dyrkning af planter til fremstilling af drikkevarer | B23: 01.27.00 | C23: Dyrkning af planter til fremstilling af drikkevarer | D23: Branchen omfatter dyrkning af planter til fremstilling af drikkevarer, fx kaffe og te.
A24: =B24 & " " & C24 -> 01.28.00 Dyrkning af krydderiplanter, aromaplanter og lægeplanter | B24: 01.28.00 | C24: Dyrkning af krydderiplanter, aromaplanter og lægeplanter | D24: Branchen omfatter dyrkning af krydderiplanter, aromaplanter og lægeplanter som fx peber, chilipeber, muskatnødder, anis, kartemomme, kanel, ingefær, vanilje og humle.
A25: =B25 & " " & C25 -> 01.29.00 Dyrkning af andre flerårige afgrøder | B25: 01.29.00 | C25: Dyrkning af andre flerårige afgrøder | D25: Branchen omfatter dyrkning af andre flerårige afgrøder, fx juletræer, træer til udvinding af træsaft og plantemateriale til brug for fletning. Branchen omfatter også dyrkning af gummitræer til udvinding af latex.
A26: =B26 & " " & C26 -> 01.30.00 Planteformering | B26: 01.30.00 | C26: Planteformering | D26: Branchen omfatter fremstilling af stiklinger, rodskud, sideskud og kimplanter til direkte planteformering eller med henblik på podning til eventuel udplantning.
A27: =B27 & " " & C27 -> 01.41.00 Avl af malkekvæg | B27: 01.41.00 | C27: Avl af malkekvæg | D27: Branchen omfatter opdræt og avl af malkekvæg, fx produktion af råmælk fra køer eller bøfler og produktion af tyresæd af mælkeracer.
A28: =B28 & " " & C28
A29: =B29 & " " & C29 | D29: Forarbejdning af mælk henvises til 10.51.00.
A30: =B30 & " " & C30 -> 01.42.00 Avl af andet kvæg og bøfler | B30: 01.42.00 | C30: Avl af andet kvæg og bøfler | D30: Branchen omfatter opdræt og avl af andet kvæg og bøfler til kødproduktion samt produktion af tyresæd.
A31: =B31 & " " & C31 -> 01.43.00 Avl af heste og dyr af hestefamilien | B31: 01.43.00 | C31: Avl af heste og dyr af hestefamilien | D31: Branchen omfatter opdræt og avl af heste og dyr af hestefamilien, fx æsler, muldyr og mulæsler.
A32: =B32 & " " & C32
A33: =B33 & " " & C33 | D33: Drift af stalde for væddeløbsheste og rideskoler henvises til 93.19.00.
A34: =B34 & " " & C34 -> 01.44.00 Avl af kameler og dyr af kamelfamilien | B34: 01.44.00 | C34: Avl af kameler og dyr af kamelfamilien | D34: Branchen omfatter opdræt og avl af kameler og dyr af kamelfamilien, fx dromedarer.
A35: =B35 & " " & C35 -> 01.45.00 Avl af får og geder | B35: 01.45.00 | C35: Avl af får og geder | D35: Branchen omfatter opdræt og avl af får og geder samt produktion af rå fåremælk og gedemælk samt råuld.
A36: =B36 & " " & C36 -> 01.46.10 Avl af smågrise | B36: 01.46.10 | C36: Avl af smågrise | D36: Branchen omfatter avl af smågrise.
A37: =B37 & " " & C37 -> 01.46.20 Produktion af slagtesvin | B37: 01.46.20 | C37: Produktion af slagtesvin | D37: Branchen omfatter opdræt og avl af slagtesvin.
A38: =B38 & " " & C38 -> 01.47.00 Fjerkræavl | B38: 01.47.00 | C38: Fjerkræavl | D38: Branchen omfatter opdræt og avl af fjerkræ, fx høns, kalkuner, ænder, gæs og perlehøns. Branchen omfatter også ægproduktion og drift af fjerkrærugerier.
A39: =B39 & " " & C39
A40: =B40 & " " & C40 | D40: Produktion af fjer og dun henvises til 10.12.00.
A41: =B41 & " " & C41 -> 01.48.00 Avl af andre dyr | B41: 01.48.00 | C41: Avl af andre dyr | D41: Branchen omfatter opdræt og avl af kæledyr, krybdyr, orme og biavl, bortset fra fisk. Branchen omfatter også produktion af skind fra opdrættede krybdyr eller fugle.
A42: =B42 & " " & C42 -> 01.50.00 Blandet landbrugsdrift | B42: 01.50.00 | C42: Blandet landbrugsdrift | D42: Branchen omfatter kombineret produktion af afgrøder og dyr, hvor hverken produktion af afgrøder eller opdræt og avl af dyr er klart dominerende i indtjeningen.
A43: =B43 & " " & C43 -> 01.61.00 Støtteaktiviteter i forbindelse med planteavl | B43: 01.61.00 | C43: Støtteaktiviteter i forbindelse med planteavl | D43: Branchen omfatter tjenesteydelser på honorar- eller kontraktbasis i forbindelse med planteavl, fx sprøjtning af afgrøder, beskæring af frugttræer, høst, skadedyrsbekæmpelse (herunder kaniner) inden for landbrug, markvandingsudstyr, udlejning af landbrugsmaskiner med betjeningspersonale og mandskab.
A44: =B44 & " " & C44
A45: =B45 & " " & C45 | D45: Forarbejdning af afgrøder efter høst henvises til 01.63.00.
A46: =B46 & " " & C46 -> 01.62.00 Støtteaktiviteter i forbindelse med husdyravl | B46: 01.62.00 | C46: Støtteaktiviteter i forbindelse med husdyravl | D46: Branchen omfatter tjenesteydelser på honoar - eller kontraktbasis i forbindelse med husdyravl, fx beslagsmedes aktiviteter, fåreklipning, opstaldning og pasning af husdyr samt aktiviteter i forbindelse med kunstig inseminering.
A47: =B47 & " " & C47 -> 01.63.00 Forarbejdning af afgrøder efter høst af frø/sædekorn til udsæd | B47: 01.63.00 | C47: Forarbejdning af afgrøder efter høst af frø/sædekorn til udsæd | D47: Branchen omfatter aktiviteter på honorar- eller kontraktbasis i forbindelse med forarbejdning af afgrøder, fx rensning, kunstig modning af frugt som serviceydelse, tørring og voksning af frugt mv.
A48: =B48 & " " & C48 -> 01.70.00 Jagt, fældefangst og serviceydelser i forbindelse hermed | B48: 01.70.00 | C48: Jagt, fældefangst og serviceydelser i forbindelse hermed | D48: Branchen omfatter jagt og fældefangst på kommerciel basis samt fangst af dyr med henblik på produktion af fødevarer og pelsværk eller til anvendelse inden for forskning, i zoologiske haver eller som kæledyr.
A49: =B49 & " " & C49
A50: =B50 & " " & C50 | D50: Branchen omfatter også landbaseret fangst af havpattedyr som fx hvalrosser og sæler.
A51: =B51 & " " & C51 -> 02.10.00 Dyrkning af træer og andre skovbrugsaktiviteter | B51: 02.10.00 | C51: Dyrkning af træer og andre skovbrugsaktiviteter | D51: Branchen omfatter dyrkning af træer og andre skovbrugsaktiviteter, fx dyrkning af skovtræer, lavskov og drift af skovplanteskoler.
A52: =B52 & " " & C52
A53: =B53 & " " & C53 | D53: Dyrkning af juletræer henvises til 01.29.00 og drift af træplanteskoler, undtagen skovtræer, henvises til 01.30.00.
A54: =B54 & " " & C54 -> 02.20.00 Skovning | B54: 02.20.00 | C54: Skovning | D54: Branchen omfatter produktion af rundtømmer, indsamling og produktion af træ og træhugningsaffald til energi samt fremstilling af trækul i skoven.
A55: =B55 & " " & C55 -> 02.30.00 Indsamling af vildtvoksende forstmateriale, undtagen træer | B55: 02.30.00 | C55: Indsamling af vildtvoksende forstmateriale, undtagen træer | D55: Branchen omfatter indsamling af vildtvoksende forstmateriale, fx bær, svampe, nødder, mos og ålegræs.
A56: =B56 & " " & C56 -> 02.40.00 Støtteaktiviteter i forbindelse med skovbrug | B56: 02.40.00 | C56: Støtteaktiviteter i forbindelse med skovbrug | D56: Branchen omfatter serviceydelser til skovbrug, såsom konsulentbistand, skadedyrsbekæmpelse samt transport af træstammer i skoven og udlejning af skovbrugsmaskiner.
A57: =B57 & " " & C57 -> 03.11.00 Havfiskeri | B57: 03.11.00 | C57: Havfiskeri | D57: Branchen omfatter havfiskeri på kommerciel basis, fx fangst og indsamling af vildtlevende fisk, krebs, hvaler, skildpadder, søpindsvin mv. i hav og kystfarvande.
A58: =B58 & " " & C58 -> 03.12.00 Ferskvandsfiskeri | B58: 03.12.00 | C58: Ferskvandsfiskeri | D58: Branchen omfatter ferskvandsfiskeri på kommerciel basis samt fangst og indsamling af fisk, krebs- og bløddyr samt andre ferskvandslevende organismer i ferskvand.
A59: =B59 & " " & C59 -> 03.21.00 Havbrug | B59: 03.21.00 | C59: Havbrug | D59: Branchen omfatter opdræt i saltvand, fx af fisk, skaldyr og bløddyr samt opdræt af yngel og dyrkning af tang. Akvakulturaktiviteter i brakvand er også omfattet.
A60: =B60 & " " & C60 -> 03.22.00 Ferskvandsbrug | B60: 03.22.00 | C60: Ferskvandsbrug | D60: Branchen omfatter opdræt i ferskvand, fx af fisk, krebs og bløddyr samt fiskeklækkerier og frøopdræt. Dyrkning af tang og alger er også omfattet.
A61: =B61 & " " & C61 -> 03.30.00 Støtteaktiviteter i forbindelse med fiskeri og akvakultur | B61: 03.30.00 | C61: Støtteaktiviteter i forbindelse med fiskeri og akvakultur | D61: Branchen omfatter serviceydelser til fiskeri eller akvakultur, fx fiskerikontrol og dykkerydelser til akvakultur.
A62: =B62 & " " & C62
A63: =B63 & " " & C63 | D63: Forarbejdning af fisk og andre akvakulturprodukter på fabriksskibe eller på fabrikker på land henvises til 10.20.20.
A64: =B64 & " " & C64 -> 05.10.00 Indvinding af stenkul | B64: 05.10.00 | C64: Indvinding af stenkul | D64: Branchen omfatter under- eller overjordisk indvinding af stenkul.
A65: =B65 & " " & C65 -> 05.20.00 Indvinding af brunkul | B65: 05.20.00 | C65: Indvinding af brunkul | D65: Branchen omfatter indvinding af fast mineralsk brændstof som fx brunkul, herunder også vask, tørring, pulverisering mv. af brunkul med henblik på kvalitetsforbedring, transport eller opbevaring.
A66: =B66 & " " & C66 -> 06.10.00 Indvinding af råolie | B66: 06.10.00 | C66: Indvinding af råolie | D66: Branchen omfatter indvinding af råolie og produktion af råolie fra asfaltskifer og olieholdigt sand.
A67: =B67 & " " & C67
A68: =B68 & " " & C68 | D68: Genvinding af flydende gas i forbindelse med raffinering af råolie henvises til 19.20.00.
A69: =B69 & " " & C69 -> 06.20.00 Indvinding af naturgas | B69: 06.20.00 | C69: Indvinding af naturgas | D69: Branchen omfatter produktion af naturgas og afsvovling af gas.
A70: =B70 & " " & C70 -> 07.10.00 Brydning af jernmalm | B70: 07.10.00 | C70: Brydning af jernmalm | D70: Branchen omfatter brydning af malm, oparbejdning og agglomerering af jernmalm.
A71: =B71 & " " & C71
A72: =B72 & " " & C72 | D72: Brydning og forarbejdning af svovlkis og pyrrhotit henvises til 08.91.00.
A73: =B73 & " " & C73 -> 07.21.00 Brydning af uran- og thoriummalme | B73: 07.21.00 | C73: Brydning af uran- og thoriummalme | D73: Branchen omfatter brydning af malme, som hovedsageligt indvindes pga. indholdet af uran og thorium. Branchen omfatter også koncentrering af disse malme samt fremstilling af yellow cake.
A74: =B74 & " " & C74
A75: =B75 & " " & C75 | D75: Berigelse af uran og thoriummalme henvises til 20.13.00.
A76: =B76 & " " & C76 -> 07.29.00 Brydning af andre ikke-jernholdige metalmalme | B76: 07.29.00 | C76: Brydning af andre ikke-jernholdige metalmalme | D76: Branchen omfatter brydning af andre ikke-jernholdige malme som fx kobber, bly, zink, tin, mangan, krom, nikkel mv., samt ædelmetallerne guld, sølv og platin.
A77: =B77 & " " & C77
A78: =B78 & " " & C78 | D78: Produktion af kobbersten henvises til 24.44.00 og produktion af nikkelsten henvises til 24.45.00.
A79: =B79 & " " & C79 -> 08.11.00 Brydning af pyntesten, kalksten, gips, skifer mv. | B79: 08.11.00 | C79: Brydning af pyntesten, kalksten, gips, skifer mv. | D79: Branchen omfatter brydning, hugning, knusning og grov tildannelse af monument- og byggesten (granit, sandsten og marmor), kalksten, gips, anhydrit, kridt og ukalcineret dolomit. Branchen omfatter endvidere produktion af granulat, flis og pulver af indvundet sten.
A80: =B80 & " " & C80 -> 08.12.00 Grus- og sandgravning og indvinding af ler og kaolin | B80: 08.12.00 | C80: Grus- og sandgravning og indvinding af ler og kaolin | D80: Branchen omfatter indvinding og pumpning af industrisand, sand til byggerier og grus samt brydning og knusning af grus. Branchen omfatter også indvinding af ler, sand og kaolin.
A81: =B81 & " " & C81
A82: =B82 & " " & C82 | D82: Indvinding af olieholdigt sand henvises til 06.10.00
A83: =B83 & " " & C83 | D83: .
A84: =B84 & " " & C84 -> 08.91.00 Indvinding af mineraler til fremstilling af kemiske produkter og gødningsstoffer | B84: 08.91.00 | C84: Indvinding af mineraler til fremstilling af kemiske produkter og gødningsstoffer | D84: Branchen omfatter indvinding af naturlige fosfater, kaliumsalte, frit svovl, naturlige magnesiumsulfater, jordpigmenter mv., som hovedsaglig udnyttes som kilde til kemiske stoffer.
A85: =B85 & " " & C85 -> 08.92.00 Indvinding af tørv | B85: 08.92.00 | C85: Indvinding af tørv | D85: Branchen omfatter tørvegravning og forarbejdning for at forbedre kvaliteten, lette transporten eller opbevaringen af tørv.
A86: =B86 & " " & C86
A87: =B87 & " " & C87 | D87: Fremstilling af tørveprodukter eller tørvebriketter henvises til hhv. 23.99.90 og 19.20.00.
A88: =B88 & " " & C88 -> 08.93.00 Saltindvinding | B88: 08.93.00 | C88: Saltindvinding | D88: Branchen omfatter indvinding af salt fra undergrunden ved opløsning og pumpning. Branchen omfatter også knusning, oprensning og raffinering af salt udført af producenten.
A89: =B89 & " " & C89
A90: =B90 & " " & C90 | D90: Fremstilling af bordsalt henvises til 10.84.00.
A91: =B91 & " " & C91 -> 08.99.00 Anden råstofindvinding i.a.n. | B91: 08.99.00 | C91: Anden råstofindvinding i.a.n. | D91: Branchen omfatter indvinding og brydning af forskellige mineraler og materialer, fx slibematerialer, asbest, fossilt kiselmel, naturligt grafit, fedtsten, ædelsten mv.
A92: =B92 & " " & C92 -> 09.10.00 Støtteaktiviteter i forbindelse med indvinding af råolie og naturgas | B92: 09.10.00 | C92: Støtteaktiviteter i forbindelse med indvinding af råolie og naturgas | D92: Branchen omfatter serviceydelser (på honorar- eller kontraktbasis) i forbindelse med indvinding af råolie og naturgas, som fx opførelse, reparation eller demontering af boretårne samt prøveboringer eller brandslukning i forbindelse med olie- eller gasindvinding.
A93: =B93 & " " & C93
A94: =B94 & " " & C94 | D94: Geologiske undersøgelser henvises til 71.12.40.
A95: =B95 & " " & C95 -> 09.90.00 Støtteaktiviteter i forbindelse med anden råstofindvinding | B95: 09.90.00 | C95: Støtteaktiviteter i forbindelse med anden råstofindvinding | D95: Branchen omfatter støtteaktiviteter (på honorar- eller kontraktbasis) i forbindelse med råstofindvinding, fx efterforskning ved at udtage boreprøver og lave geologiske observationer. Branchen omfatter også serviceydelser i forbindelse med dræning og pumpning.
A96: =B96 & " " & C96
A97: =B97 & " " & C97 | D97: Geofysiske undersøgelser på honorar- eller kontraktbasis henvises til 71.12.40.
A98: =B98 & " " & C98 -> 10.11.10 Forarbejdning af svinekød | B98: 10.11.10 | C98: Forarbejdning af svinekød | D98: Branchen omfatter drift af svineslagterier, aflivning, forarbejdning eller emballering, herunder fremstilling af fersk, kølet eller frossent svinekød i hele kroppe eller udskæringer. Branchen omfatter også forarbejdning af svinefedt og slagteaffald.
A99: =B99 & " " & C99 -> 10.11.90 Forarbejdning af andet kød | B99: 10.11.90 | C99: Forarbejdning af andet kød | D99: Branchen omfatter slagtning af andre dyr end svin og fjerkræ, aflivning, forarbejdning eller emballering herunder fremstilling af fersk, kølet eller frossent kød i hele kroppe eller udskæringer. Fremstilling af kradsuld er også omfattet.
A100: =B100 & " " & C100
...
